{
  "skills": [
    {
      "category": {
        "pt": "Frontend",
        "en": "Frontend"
      },
      "items": ["React", "React Native", "TypeScript", "Next.js", "Tailwind CSS", "Framer Motion"]
    },
    {
      "category": {
        "pt": "Backend",
        "en": "Backend"
      },
      "items": ["NestJS", "Node.js", "Express", "GraphQL", "REST APIs", "Microservices"]
    },
    {
      "category": {
        "pt": "Banco de Dados",
        "en": "Database"
      },
      "items": ["PostgreSQL", "MongoDB", "Redis", "Prisma", "TypeORM", "Supabase"]
    },
    {
      "category": {
        "pt": "DevOps & Ferramentas",
        "en": "DevOps & Tools"
      },
      "items": ["Docker", "AWS", "Git", "GitHub Actions", "Jest", "Cypress"]
    }
  ]
}